{
	"stacks": {
		"stack1" :{
			"keys": ["original.energy"],
			"labels": ["Energy"],
			"colors": ["#9f7ccf"]
		},
		"stack2" :{
			"keys": ["all_cf_pes.energy"],
			"labels": ["Energy"],
			"colors": ["#9f7ccf"]
		},
		"stack3" :{
			"keys": ["fused_into_pe.energy"],
			"labels": ["Energy"],
			"colors": ["#9f7ccf"]
		},
		"stack4" :{
			"keys": ["physical./flow_top/CGRA.energy.total"],
			"labels": ["Energy"],
			"colors": ["#9f7ccf"]
		}
	},
	"srcs": [
		[
			{
				"src": "../data/compress/dmv_fused_into_pe.json",
				"label": "RipTide",
				"stack": "stack1",
				"normalize": {
					"src": "../data/compress/dmv_fused_into_pe.json",
					"stack": "stack1"
				}
			},
			{
				"src": "../data//compress/xrun/large/dmv/flow/flow/no_fin/result.json",
				"label": "No CFiN",
				"stack": "stack4",
				"normalize": {
					"src": "../data/compress/dmv_fused_into_pe.json",
					"stack": "stack1"
				}
			},
			{
				"src": "../data//compress/xrun/large/dmv/flow/flow/no_fin/result.json",
				"label": "All PEs",
				"stack": "stack4",
				"normalize": {
					"src": "../data/compress/dmv_fused_into_pe.json",
					"stack": "stack1"
				}
			},
			{
				"src": "../data/compress/dmv_fused_into_pe.json",
				"label": "Fused",
				"stack": "stack3",
				"normalize": {
					"src": "../data/compress/dmv_fused_into_pe.json",
					"stack": "stack1"
				}
			}
		],
		[
			{
				"src": "../data/compress/dmm_fused_into_pe.json",
				"label": "",
				"stack": "stack1",
				"normalize": {
					"src": "../data/compress/dmm_fused_into_pe.json",
					"stack": "stack1"
				}
			},
			{
				"x": true,
				"src": "../data/compress/dmm_fused_into_pe.json",
				"label": "",
				"stack": "stack2",
				"normalize": {
					"src": "../data/compress/dmm_fused_into_pe.json",
					"stack": "stack1"
				}
			},
			{
				"src": "../data/compress/dmm_fused_into_pe.json",
				"label": "",
				"stack": "stack2",
				"normalize": {
					"src": "../data/compress/dmm_fused_into_pe.json",
					"stack": "stack1"
				}
			},
			{
				"src": "../data/compress/dmm_fused_into_pe.json",
				"label": "",
				"stack": "stack3",
				"normalize": {
					"src": "../data/compress/dmm_fused_into_pe.json",
					"stack": "stack1"
				}
			}
		],
		[
			{
				"src": "../data/compress/dconv_fused_into_pe.json",
				"label": "",
				"stack": "stack1",
				"normalize": {
					"src": "../data/compress/dconv_fused_into_pe.json",
					"stack": "stack1"
				}
			},
			{
				"x": true,
				"src": "../data/compress/dconv_fused_into_pe.json",
				"label": "",
				"stack": "stack2",
				"normalize": {
					"src": "../data/compress/dconv_fused_into_pe.json",
					"stack": "stack1"
				}
			},
			{
				"src": "../data/compress/dconv_fused_into_pe.json",
				"label": "",
				"stack": "stack2",
				"normalize": {
					"src": "../data/compress/dconv_fused_into_pe.json",
					"stack": "stack1"
				}
			},
			{
				"src": "../data/compress/dconv_fused_into_pe.json",
				"label": "",
				"stack": "stack3",
				"normalize": {
					"src": "../data/compress/dconv_fused_into_pe.json",
					"stack": "stack1"
				}
			}
		],
		[
			{
				"src": "../data/compress/smv_fused_into_pe.json",
				"label": "",
				"stack": "stack1",
				"normalize": {
					"src": "../data/compress/smv_fused_into_pe.json",
					"stack": "stack1"
				}
			},
			{
				"src": "../data//compress/xrun/large/smv/flow/flow/no_fin/result.json",
				"label": "",
				"stack": "stack4",
				"normalize": {
					"src": "../data/compress/smv_fused_into_pe.json",
					"stack": "stack1"
				}
			},
			{
				"src": "../data//compress/xrun/large/smv/flow/flow/no_fin/result.json",
				"label": "",
				"stack": "stack4",
				"normalize": {
					"src": "../data/compress/smv_fused_into_pe.json",
					"stack": "stack1"
				}
			},
			{
				"src": "../data/compress/smv_fused_into_pe.json",
				"label": "",
				"stack": "stack3",
				"normalize": {
					"src": "../data/compress/smv_fused_into_pe.json",
					"stack": "stack1"
				}
			}
		],
		[
			{
				"src": "../data/compress/smm_fused_into_pe.json",
				"label": "",
				"stack": "stack1",
				"normalize": {
					"src": "../data/compress/smm_fused_into_pe.json",
					"stack": "stack1"
				}
			},
			{
				"x": true,
				"src": "../data/compress/smm_fused_into_pe.json",
				"label": "",
				"stack": "stack2",
				"normalize": {"src": "../data/compress/smm_fused_into_pe.json",
					"stack": "stack1"
				}
			},
			{
				"src": "../data/compress/smm_fused_into_pe.json",
				"label": "",
				"stack": "stack2",
				"normalize": {
					"src": "../data/compress/smm_fused_into_pe.json",
					"stack": "stack1"
				}
			},
			{
				"src": "../data/compress/smm_fused_into_pe.json",
				"label": "",
				"stack": "stack3",
				"normalize": {
					"src": "../data/compress/smm_fused_into_pe.json",
					"stack": "stack1"
				}
			}
		],
		[
			{
				"src": "../data/compress/sconv_fused_into_pe.json",
				"label": "",
				"stack": "stack1",
				"normalize": {
					"src": "../data/compress/sconv_fused_into_pe.json",
					"stack": "stack1"
				}
			},
			{
				"x": true,
				"src": "../data/compress/sconv_fused_into_pe.json",
				"label": "",
				"stack": "stack2",
				"normalize": {
					"src": "../data/compress/sconv_fused_into_pe.json",
					"stack": "stack1"
				}
			},
			{
				"src": "../data/compress/sconv_fused_into_pe.json",
				"label": "",
				"stack": "stack2",
				"normalize": {
					"src": "../data/compress/sconv_fused_into_pe.json",
					"stack": "stack1"
				}
			},
			{
				"src": "../data/compress/sconv_fused_into_pe.json",
				"label": "",
				"stack": "stack3",
				"normalize": {
					"src": "../data/compress/sconv_fused_into_pe.json",
					"stack": "stack1"
				}
			}
		],
		[
			{
				"src": "../data/compress/sort_fused_into_pe.json",
				"label": "",
				"stack": "stack1",
				"normalize": {
					"src": "../data/compress/sort_fused_into_pe.json",
					"stack": "stack1"
				}
			},
			{
				"x": true,
				"src": "../data/compress/sort_fused_into_pe.json",
				"label": "",
				"stack": "stack2",
				"normalize": {
					"src": "../data/compress/sort_fused_into_pe.json",
					"stack": "stack1"
				}
			},
			{
				"src": "../data/compress/sort_fused_into_pe.json",
				"label": "",
				"stack": "stack2",
				"normalize": {
					"src": "../data/compress/sort_fused_into_pe.json",
					"stack": "stack1"
				}
			},
			{
				"src": "../data/compress/sort_fused_into_pe.json",
				"label": "",
				"stack": "stack3",
				"normalize": {
					"src": "../data/compress/sort_fused_into_pe.json",
					"stack": "stack1"
				}
			}
		],
		[
			{
				"src": "../data/compress/fft_fused_into_pe.json",
				"label": "",
				"stack": "stack1",
				"normalize": {
					"src": "../data/compress/fft_fused_into_pe.json",
					"stack": "stack1"
				}
			},
			{
				"x": true,
				"src": "../data/compress/fft_fused_into_pe.json",
				"label": "",
				"stack": "stack2",
				"normalize": {
					"src": "../data/compress/fft_fused_into_pe.json",
					"stack": "stack1"
				}
			},
			{
				"src": "../data/compress/fft_fused_into_pe.json",
				"label": "",
				"stack": "stack2",
				"normalize": {
					"src": "../data/compress/fft_fused_into_pe.json",
					"stack": "stack1"
				}
			},
			{
				"src": "../data/compress/fft_fused_into_pe.json",
				"label": "",
				"stack": "stack3",
				"normalize": {
					"src": "../data/compress/fft_fused_into_pe.json",
					"stack": "stack1"
				}
			}
		],
		[
			{
				"src": "../data/compress/bfs_fused_into_pe.json",
				"label": "",
				"stack": "stack1",
				"normalize": {
					"src": "../data/compress/bfs_fused_into_pe.json",
					"stack": "stack1"
				}
			},
			{
				"x": true,
				"src": "../data/compress/bfs_fused_into_pe.json",
				"label": "",
				"stack": "stack2",
				"normalize": {
					"src": "../data/compress/bfs_fused_into_pe.json",
					"stack": "stack1"
				}
			},
			{
				"src": "../data/compress/bfs_fused_into_pe.json",
				"label": "",
				"stack": "stack2",
				"normalize": {
					"src": "../data/compress/bfs_fused_into_pe.json",
					"stack": "stack1"
				}
			},
			{
				"src": "../data/compress/bfs_fused_into_pe.json",
				"label": "",
				"stack": "stack3",
				"normalize": {
					"src": "../data/compress/bfs_fused_into_pe.json",
					"stack": "stack1"
				}
			}
		],
		[
			{
				"src": "../data/compress/dfs_fused_into_pe.json",
				"label": "",
				"stack": "stack1",
				"normalize": {
					"src": "../data/compress/dfs_fused_into_pe.json",
					"stack": "stack1"
				}
			},
			{
				"x": true,
				"src": "../data/compress/dfs_fused_into_pe.json",
				"label": "",
				"stack": "stack2",
				"normalize": {
					"src": "../data/compress/dfs_fused_into_pe.json",
					"stack": "stack1"
				}
			},
			{
				"src": "../data/compress/dfs_fused_into_pe.json",
				"label": "",
				"stack": "stack2",
				"normalize": {
					"src": "../data/compress/dfs_fused_into_pe.json",
					"stack": "stack1"
				}
			},
			{
				"src": "../data/compress/dfs_fused_into_pe.json",
				"label": "",
				"stack": "stack3",
				"normalize": {
					"src": "../data/compress/dfs_fused_into_pe.json",
					"stack": "stack1"
				}
			}
		]
	],
	"sci_not": true,
	"major": ["DMV", "DMM", "DConv", "SMV", "SMM", "SConv", "Sort", "FFT", "BFS", "DFS"],
	"width": 10,
	"height": 5,
	"xlim": [2, 97],
	"ylim": 3,
	"rect": [0, 0, 1, 0.9],
	"minor_spacing": 2,
	"major_spacing": 1.5,
	"minor_annotate": true,
	"major_padding": 5,
	"barwidth": 1.1,
	"fontsize": 18,
	"ylabel": "Energy"
}
